basalam.backbone_redis_cache-0.0.13-py3.13-nspkg.pth
basalam/backbone_redis_cache/__init__.py
basalam/backbone_redis_cache/redis_cache.py
basalam_backbone_redis_cache-0.0.13.dist-info/METADATA
basalam_backbone_redis_cache-0.0.13.dist-info/WHEEL
basalam_backbone_redis_cache-0.0.13.dist-info/namespace_packages.txt
basalam_backbone_redis_cache-0.0.13.dist-info/top_level.txt
basalam_backbone_redis_cache-0.0.13.dist-info/RECORD
