Metadata-Version: 2.4
Name: basalam.backbone-redis-cache
Version: 0.0.13
Summary: Python Utilities & Basalam Micro-Services SDK
Home-page: https://github.com/basalam/backbone-redis-cache
Author: Mojtabaa Habibain
Author-email: mojtabaa.hn@gmail.com
Classifier: Programming Language :: Python :: 3
Classifier: License :: OSI Approved :: MIT License
Classifier: Operating System :: OS Independent
Requires-Python: >=3.6
Requires-Dist: redis>=4.4.4
Requires-Dist: aioredis==2.0.1
Dynamic: author
Dynamic: author-email
Dynamic: classifier
Dynamic: description
Dynamic: description-content-type
Dynamic: home-page
Dynamic: requires-dist
Dynamic: requires-python
Dynamic: summary
